regsyn/__init__.py
regsyn/_modidx.py
regsyn/core.py
regsyn-0.0.3.dist-info/LICENSE
regsyn-0.0.3.dist-info/METADATA
regsyn-0.0.3.dist-info/WHEEL
regsyn-0.0.3.dist-info/entry_points.txt
regsyn-0.0.3.dist-info/top_level.txt
regsyn-0.0.3.dist-info/RECORD
