Metadata-Version: 2.1
Name: regsyn
Version: 0.0.3
Summary: Register Synonyms
Home-page: https://github.com/dsm-72/regsyn
Author: dsm-72
Author-email: sumner.magruder@yale.edu
License: Apache Software License 2.0
Keywords: reg syn register synonyms alias function globals pollution globsyn regsyn regsyns
Classifier: Development Status :: 4 - Beta
Classifier: Intended Audience :: Developers
Classifier: Natural Language :: English
Classifier: Programming Language :: Python :: 3.11
Classifier: License :: OSI Approved :: Apache Software License
Requires-Python: >=3.11
License-File: LICENSE
Provides-Extra: dev
